[
  {
    "id": "prod-1",
    "name": "ไมโครโฟนไร้สาย Wireless Microphone สำหรับแคสเกมและทำคลิป",
    "originalUrl": "https://shopee.co.th/search?keyword=ไมโครโฟนไร้สาย",
    "description": "ไมโครโฟนไร้สายขนาดเล็ก เสียงคมชัด ตัดเสียงรบกวนรอบข้างดีเยี่ยม เหมาะสำหรับทำคลิป TikTok / Shorts",
    "videoSource": "https://commondatastorage.googleapis.com/gtv-videos-bucket/sample/ForBiggerEscapes.mp4"
  },
  {
    "id": "prod-2",
    "name": "เครื่องชงกาแฟเอสเพรสโซ่ขนาดพกพา Portable Espresso Maker",
    "originalUrl": "https://shopee.co.th/search?keyword=เครื่องชงกาแฟเอสเพรสโซ่พกพา",
    "description": "เครื่องชงกาแฟพกพา ไม่ต้องใช้ไฟฟ้า แค่เติมน้ำร้อนและแคปซูล/ผงกาแฟ ก็ได้เอสเพรสโซ่เข้มข้นทุกที่",
    "videoSource": "https://commondatastorage.googleapis.com/gtv-videos-bucket/sample/ForBiggerFun.mp4"
  },
  {
    "id": "prod-3",
    "name": "คีย์บอร์ดกลไกไร้สาย Retro Mechanical Keyboard",
    "originalUrl": "https://shopee.co.th/search?keyword=คีย์บอร์ดกลไกไร้สาย",
    "description": "คีย์บอร์ดปุ่มกดเสียงบลูสวิตช์สุดฟิน ดีไซน์พิมพ์ดีดโบราณ ไฟ RGB สวยงาม เชื่อมต่อบลูทูธได้ 3 อุปกรณ์",
    "videoSource": "https://commondatastorage.googleapis.com/gtv-videos-bucket/sample/ForBiggerJoyrides.mp4"
  },
  {
    "id": "prod-4",
    "name": "โคมไฟตั้งโต๊ะพระจันทร์ 3D Magnetic Floating Moon Lamp",
    "originalUrl": "https://shopee.co.th/search?keyword=โคมไฟดวงจันทร์",
    "description": "โคมไฟพระจันทร์ลอยได้แบบแม่เหล็ก หมุนได้รอบตัว เปลี่ยนสีไฟได้ 3 โทนสี แต่งห้องนอนหรูหราไฮเทคสุดๆ",
    "videoSource": "https://commondatastorage.googleapis.com/gtv-videos-bucket/sample/ForBiggerBlazes.mp4"
  },
  {
    "id": "prod-5",
    "name": "เครื่องให้อาหารสัตว์เลี้ยงอัตโนมัติ Smart Automatic Pet Feeder",
    "originalUrl": "https://shopee.co.th/search?keyword=เครื่องให้อาหารสัตว์เลี้ยงอัตโนมัติ",
    "description": "ถังอาหารหมาแมวอัจฉริยะ ตั้งเวลาและปริมาณอาหารผ่านแอปบนมือถือได้ มีกล้องพูดคุยตอบโต้ได้เรียลไทม์",
    "videoSource": "https://commondatastorage.googleapis.com/gtv-videos-bucket/sample/ForBiggerMeltdowns.mp4"
  }
]
